[
    {
    "name": "The Thompsons",
    "genre": "Rock",
    "bio": "The Thompsons are a rock group from Paris, France.",
    "website": "thompsonstour.com",
    "phone": "1234567890"
    },
    {
    "name": "Pop and Pop",
    "genre": "Pop",
    "bio": "Pop and Pop are a pop band from Utah.",
    "website": "popandpop.com",
    "phone": "1234567890"
    },
    {
    "name": "Metal Beards",
    "genre": "Metal",
    "bio": "Lots of metal. Lots of beards.",
    "website": "metalbeardsband.com",
    "phone": "1234567890"
    },
    {
    "name": "Chandler Bing",
    "genre": "Rap",
    "bio": "Chandler Bing is the hottest new rapper from Vancouver.",
    "website": "bingbling.com",
    "phone": "1234567890"
    },
    {
    "name": "Horses Blue",
    "genre": "Country",
    "bio": "Country band from Georgia.",
    "website": "bluehorses.com",
    "phone": "1234567890"
    }
  ]